fastapi_storage/__init__.py
fastapi_storage/filesystem.py
fastapi_storage/filesystem_adapter.py
fastapi_storage/filesystem_manager.py
fastapi_storage/main.py
fastapi_storage/obs_adapter.py
fastapi_storage/oss_adapter.py
fastapi_storage/upload.py
fastapi_storage/contracts/__init__.py
fastapi_storage/contracts/filesystem/__init__.py
fastapi_storage/contracts/filesystem/cloud.py
fastapi_storage/contracts/filesystem/factory.py
fastapi_storage/contracts/filesystem/filesystem.py
fastapi_storage/core/__init__.py
fastapi_storage/core/settings.py
fastapi_storage-1.0.2.dist-info/LICENSE
fastapi_storage-1.0.2.dist-info/METADATA
fastapi_storage-1.0.2.dist-info/WHEEL
fastapi_storage-1.0.2.dist-info/entry_points.txt
fastapi_storage-1.0.2.dist-info/top_level.txt
fastapi_storage-1.0.2.dist-info/zip-safe
fastapi_storage-1.0.2.dist-info/RECORD
